vibeisodd/__init__.py
vibeisodd/example.py
vibeisodd-1.0.0.dist-info/licenses/LICENSE
vibeisodd-1.0.0.dist-info/METADATA
vibeisodd-1.0.0.dist-info/WHEEL
vibeisodd-1.0.0.dist-info/top_level.txt
vibeisodd-1.0.0.dist-info/RECORD
