Metadata-Version: 2.4
Name: vibeisodd
Version: 1.0.0
Summary: AI-powered odd number detection using GPT
Home-page: https://github.com/yourusername/VibeIsOdd
Author: Your Name
Author-email: Your Name <your.email@example.com>
License: MIT License
Keywords: ai,gpt,numbers,odd,detection,parody
Classifier: Programming Language :: Python :: 3
Classifier: Programming Language :: Python :: 3.7
Classifier: Programming Language :: Python :: 3.8
Classifier: Programming Language :: Python :: 3.9
Classifier: Programming Language :: Python :: 3.10
Classifier: Programming Language :: Python :: 3.11
Classifier: License :: OSI Approved :: MIT License
Classifier: Operating System :: OS Independent
Classifier: Intended Audience :: Developers
Classifier: Topic :: Software Development :: Libraries :: Python Modules
Classifier: Topic :: Scientific/Engineering :: Artificial Intelligence
Requires-Python: >=3.7
License-File: LICENSE
Requires-Dist: openai>=1.0.0
Dynamic: author
Dynamic: home-page
Dynamic: license-file
Dynamic: requires-python
